odoo10_addon_purchase_variant_configurator_on_confirm-10.0.1.0.0.99.dev8-py3.8-nspkg.pth
odoo/addons/purchase_variant_configurator_on_confirm/README.rst
odoo/addons/purchase_variant_configurator_on_confirm/__init__.py
odoo/addons/purchase_variant_configurator_on_confirm/__manifest__.py
odoo/addons/purchase_variant_configurator_on_confirm/i18n/ar.po
odoo/addons/purchase_variant_configurator_on_confirm/i18n/ca.po
odoo/addons/purchase_variant_configurator_on_confirm/i18n/de.po
odoo/addons/purchase_variant_configurator_on_confirm/i18n/es.po
odoo/addons/purchase_variant_configurator_on_confirm/i18n/es_MX.po
odoo/addons/purchase_variant_configurator_on_confirm/i18n/fi.po
odoo/addons/purchase_variant_configurator_on_confirm/i18n/fr.po
odoo/addons/purchase_variant_configurator_on_confirm/i18n/fr_CH.po
odoo/addons/purchase_variant_configurator_on_confirm/i18n/hr.po
odoo/addons/purchase_variant_configurator_on_confirm/i18n/hr_HR.po
odoo/addons/purchase_variant_configurator_on_confirm/i18n/it.po
odoo/addons/purchase_variant_configurator_on_confirm/i18n/nl_NL.po
odoo/addons/purchase_variant_configurator_on_confirm/i18n/pt_BR.po
odoo/addons/purchase_variant_configurator_on_confirm/i18n/purchase_variant_configurator_on_confirm.pot
odoo/addons/purchase_variant_configurator_on_confirm/i18n/ro.po
odoo/addons/purchase_variant_configurator_on_confirm/i18n/sl.po
odoo/addons/purchase_variant_configurator_on_confirm/i18n/tr_TR.po
odoo/addons/purchase_variant_configurator_on_confirm/i18n/vi_VN.po
odoo/addons/purchase_variant_configurator_on_confirm/i18n/zh_CN.po
odoo/addons/purchase_variant_configurator_on_confirm/models/__init__.py
odoo/addons/purchase_variant_configurator_on_confirm/models/product_product.py
odoo/addons/purchase_variant_configurator_on_confirm/models/product_template.py
odoo/addons/purchase_variant_configurator_on_confirm/models/purchase_order.py
odoo/addons/purchase_variant_configurator_on_confirm/static/description/icon.png
odoo10_addon_purchase_variant_configurator_on_confirm-10.0.1.0.0.99.dev8.dist-info/METADATA
odoo10_addon_purchase_variant_configurator_on_confirm-10.0.1.0.0.99.dev8.dist-info/WHEEL
odoo10_addon_purchase_variant_configurator_on_confirm-10.0.1.0.0.99.dev8.dist-info/namespace_packages.txt
odoo10_addon_purchase_variant_configurator_on_confirm-10.0.1.0.0.99.dev8.dist-info/top_level.txt
odoo10_addon_purchase_variant_configurator_on_confirm-10.0.1.0.0.99.dev8.dist-info/RECORD
